[
  {
    "name": "Waycross Express 3258494",
    "image": "https://s7d9.scene7.com/is/image/championhomes/0612-MV-Champion-0017%20copy",
    "score": 50,
    "source": "img",
    "width": 310,
    "height": 216,
    "manufacturerUrl": "https://www.championhomes.com/models/waycross-express"
  },
  {
    "name": "Prime Manor 4523A",
    "image": "https://s7d9.scene7.com/is/image/championhomes/26-print-park-model-528-070-014%20copy",
    "score": 50,
    "source": "img",
    "width": 310,
    "height": 216,
    "manufacturerUrl": "https://www.championhomes.com/models/prime-manor-4523A"
  },
  {
    "name": "Vienna 2.0",
    "image": "https://s7d9.scene7.com/is/image/championhomes/Genesis%20510%20ADU",
    "score": 50,
    "source": "img",
    "width": 310,
    "height": 216,
    "manufacturerUrl": "https://www.championhomes.com/models/vienna-2.0"
  },
  {
    "name": "Icon 3256",
    "image": "https://s7d9.scene7.com/is/image/championhomes/Blog",
    "score": 50,
    "source": "img",
    "width": 310,
    "height": 216,
    "manufacturerUrl": "https://www.championhomes.com/models/icon-3256"
  },
  {
    "name": "Icon 2876 Talladega",
    "image": "https://s7d9.scene7.com/is/image/championhomes/0612-MV-Champion-0382_JPG%20(1)%20copy",
    "score": 50,
    "source": "img",
    "width": 310,
    "height": 216,
    "manufacturerUrl": "https://www.championhomes.com/models/icon-2876-talladega"
  },
  {
    "name": "The Maddux",
    "image": "https://s7d9.scene7.com/is/image/championhomes/Brave%203248464%20Exterior%20(1)",
    "score": 235,
    "source": "img",
    "width": 1280,
    "height": 854,
    "manufacturerUrl": "https://www.championhomes.com/models/the-maddux"
  },
  {
    "name": "Lake Manor 2444H22036",
    "image": "https://s7d9.scene7.com/is/image/championhomes/MH%20Community%2001",
    "score": 50,
    "source": "img",
    "width": 310,
    "height": 216,
    "manufacturerUrl": "https://www.championhomes.com/models/lake-manor-2444H22036"
  },
  {
    "name": "Prime Daybreak",
    "image": "https://s7d9.scene7.com/is/image/championhomes/AdobeStock_251254078",
    "score": 50,
    "source": "img",
    "width": 310,
    "height": 216,
    "manufacturerUrl": "https://www.championhomes.com/models/prime-daybreak"
  },
  {
    "name": "Prime Manor 0764D",
    "image": "https://s7d9.scene7.com/is/image/championhomes/Terms",
    "score": 50,
    "source": "img",
    "width": 310,
    "height": 216,
    "manufacturerUrl": "https://www.championhomes.com/models/prime-manor-0764D"
  },
  {
    "name": "Prime Manor 0764D",
    "image": "https://s7d9.scene7.com/is/image/championhomes/0612-MV-Champion-0097_JPG",
    "score": 50,
    "source": "img",
    "width": 310,
    "height": 216,
    "manufacturerUrl": "https://www.championhomes.com/models/prime-manor-0764D"
  },
  {
    "name": "Cypress Manor 0764E",
    "image": "https://s7d9.scene7.com/is/image/championhomes/MuddImage19",
    "score": 50,
    "source": "img",
    "width": 310,
    "height": 216,
    "manufacturerUrl": "https://www.championhomes.com/models/cypress-manor-0764B"
  },
  {
    "name": "Bozeman",
    "image": "https://s7d9.scene7.com/is/image/championhomes/050-yellowstone-3276538-main-image",
    "score": 190,
    "source": "img",
    "width": 749,
    "height": 500,
    "manufacturerUrl": "https://www.championhomes.com/models/bozeman"
  },
  {
    "name": "The Murphy",
    "image": "https://s7d9.scene7.com/is/image/championhomes/052-brave-1676-504-main-image",
    "score": 190,
    "source": "img",
    "width": 1280,
    "height": 854,
    "manufacturerUrl": "https://www.championhomes.com/models/the-murphy"
  },
  {
    "name": "Winter Special",
    "image": "https://s7d9.scene7.com/is/image/championhomes/1672H32WSP-Main-Image",
    "score": 190,
    "source": "img",
    "width": 749,
    "height": 500,
    "manufacturerUrl": "https://www.championhomes.com/models/winter-special"
  },
  {
    "name": "RH26282A",
    "image": "https://s7d9.scene7.com/is/image/championhomes/261-trininty-rh2682a-main-image",
    "score": 190,
    "source": "img",
    "width": 1280,
    "height": 854,
    "manufacturerUrl": "https://www.championhomes.com/models/rh2682a"
  },
  {
    "name": "RH1522A",
    "image": "https://s7d9.scene7.com/is/image/championhomes/Redman-Trinity-1522A-main-image",
    "score": 190,
    "source": "img",
    "width": 749,
    "height": 500,
    "manufacturerUrl": "https://www.championhomes.com/models/rh1522a"
  }
]